Metadata-Version: 2.1
Name: moscow-toponyms
Version: 0.1.0
Summary: Moscow toponym extractor for Russian texts
Home-page: https://github.com/diana-esaian/moscow_toponyms
Author: Diana Esaian
Author-email: diana.esaian@gmail.com
License: MIT
Classifier: License :: OSI Approved :: MIT License
Classifier: Programming Language :: Python :: 3
Classifier: Natural Language :: Russian
Classifier: Topic :: Text Processing
Requires-Python: >=3.6
License-File: LICENSE
